setup.py
ctbf/__init__.py
ctbf.egg-info/PKG-INFO
ctbf.egg-info/SOURCES.txt
ctbf.egg-info/dependency_links.txt
ctbf.egg-info/not-zip-safe
ctbf.egg-info/top_level.txt