Metadata-Version: 1.0
Name: ctbf
Version: 0.1.4
Summary: Crypto Trading Bot Platform
Home-page: http://github.com/storborg/funniest
Author: Sergey Bryukov
Author-email: sbryukov@gmail.com
License: MIT
Platform: UNKNOWN
